kwiksand/__init__.py
kwiksand/kwiksand.py
kwiksand-1.2.0.dist-info/METADATA
kwiksand-1.2.0.dist-info/WHEEL
kwiksand-1.2.0.dist-info/top_level.txt
kwiksand-1.2.0.dist-info/RECORD
