Metadata-Version: 2.1
Name: kwiksand
Version: 1.2.0
Summary: a thing to write text character by character
